{"stats":{"minecraft:mined":{"minecraft:oak_log":4,"minecraft:stone":1,"minecraft:oak_leaves":2},"minecraft:picked_up":{"minecraft:oak_log":4,"minecraft:oak_sapling":1,"minecraft:cobblestone":1},"minecraft:custom":{"minecraft:jump":20,"minecraft:time_since_rest":1293,"minecraft:crouch_one_cm":194,"minecraft:play_one_minute":1293,"minecraft:leave_game":1,"minecraft:sprint_one_cm":2936,"minecraft:time_since_death":1293,"minecraft:walk_one_cm":1781,"minecraft:sneak_time":35,"minecraft:fall_one_cm":1103,"minecraft:fly_one_cm":3542},"minecraft:used":{"minecraft:cobblestone":1,"enhancedcraft:etherium_axe":1,"minecraft:bone_meal":3,"minecraft:oak_sapling":1,"enhancedcraft:obsidian_axe":4}},"DataVersion":2578}